toscaparser/__init__.py
toscaparser/capabilities.py
toscaparser/dataentity.py
toscaparser/entity_template.py
toscaparser/functions.py
toscaparser/groups.py
toscaparser/imports.py
toscaparser/nodetemplate.py
toscaparser/parameters.py
toscaparser/policy.py
toscaparser/properties.py
toscaparser/relationship_template.py
toscaparser/repositories.py
toscaparser/reservation.py
toscaparser/shell.py
toscaparser/substitution_mappings.py
toscaparser/topology_template.py
toscaparser/tosca_template.py
toscaparser/tpl_relationship_graph.py
toscaparser/triggers.py
toscaparser/unsupportedtype.py
toscaparser/common/__init__.py
toscaparser/common/exception.py
toscaparser/elements/TOSCA_definition.yaml
toscaparser/elements/__init__.py
toscaparser/elements/artifacttype.py
toscaparser/elements/attribute_definition.py
toscaparser/elements/capabilitytype.py
toscaparser/elements/constraints.py
toscaparser/elements/datatype.py
toscaparser/elements/entity_type.py
toscaparser/elements/grouptype.py
toscaparser/elements/interfaces.py
toscaparser/elements/nodetype.py
toscaparser/elements/policytype.py
toscaparser/elements/portspectype.py
toscaparser/elements/property_definition.py
toscaparser/elements/relationshiptype.py
toscaparser/elements/scalarunit.py
toscaparser/elements/statefulentitytype.py
toscaparser/elements/tosca_type_validation.py
toscaparser/extensions/__init__.py
toscaparser/extensions/exttools.py
toscaparser/extensions/mec/TOSCA_mec_definition_1_0_0.yaml
toscaparser/extensions/mec/__init__.py
toscaparser/extensions/mec/tosca_simple_profile_for_mec_1_0_0.py
toscaparser/extensions/nfv/TOSCA_nfv_definition_1_0_0.yaml
toscaparser/extensions/nfv/__init__.py
toscaparser/extensions/nfv/tosca_simple_profile_for_nfv_1_0_0.py
toscaparser/prereq/__init__.py
toscaparser/prereq/csar.py
toscaparser/tests/__init__.py
toscaparser/tests/base.py
toscaparser/tests/test_constraints.py
toscaparser/tests/test_custom_relationships.py
toscaparser/tests/test_datatypes.py
tosca_parser-2.13.0.dist-info/AUTHORS
tosca_parser-2.13.0.dist-info/LICENSE
tosca_parser-2.13.0.dist-info/METADATA
tosca_parser-2.13.0.dist-info/WHEEL
tosca_parser-2.13.0.dist-info/entry_points.txt
tosca_parser-2.13.0.dist-info/pbr.json
tosca_parser-2.13.0.dist-info/top_level.txt
tosca_parser-2.13.0.dist-info/RECORD
