Metadata-Version: 2.1
Name: tosca-parser
Version: 2.13.0
Summary: Parser for TOSCA Simple Profile in YAML.
Home-page: https://docs.openstack.org/tosca-parser/latest/
Author: OpenStack
Author-email: openstack-discuss@lists.openstack.org
Classifier: Environment :: OpenStack
Classifier: Intended Audience :: Information Technology
Classifier: Intended Audience :: System Administrators
Classifier: License :: OSI Approved :: Apache Software License
Classifier: Operating System :: POSIX :: Linux
Classifier: Programming Language :: Python
Classifier: Programming Language :: Python :: Implementation :: CPython
Classifier: Programming Language :: Python :: 3 :: Only
Classifier: Programming Language :: Python :: 3
Classifier: Programming Language :: Python :: 3.6
Classifier: Programming Language :: Python :: 3.7
Classifier: Programming Language :: Python :: 3.8
Classifier: Programming Language :: Python :: 3.9
Classifier: Programming Language :: Python :: 3.10
Requires-Python: >=3.6
License-File: LICENSE
License-File: AUTHORS
Requires-Dist: pbr >=6.0.0
Requires-Dist: cliff >=4.9.1
Requires-Dist: PyYAML >=3.12
Requires-Dist: python-dateutil >=2.9.0
Requires-Dist: stevedore >=2.0.1
Requires-Dist: requests >=2.32.3
